{
  "created_at": "2026-07-15T17:12:03.554547+00:00",
  "experiment": "q2_multitask_ablation",
  "provenance": {
    "allow_silver_gold": false,
    "fine_tuning": "evaluated_from_prediction_jsonl",
    "note": "This runner evaluates prediction JSONL created by local or remote training; it does not itself train a model.",
    "predictions_dir": "/root/vipragsent-repro/results/predictions",
    "record_limit": null,
    "runner": "vipragsent.experiments.runner",
    "source_file": "/root/vipragsent-repro/results/predictions/multitask_ablation/summary.json"
  },
  "rows": {
    "explanation_augmented_inference": {
      "reason": "No inference-time rationale-generation variant is implemented in this protocol.",
      "status": "not_run"
    },
    "full": {
      "ece": 0.06711602833176075,
      "macro_pragmatic_f1": 73.7182,
      "ordinary_f1": null,
      "prediction_file": "/root/vipragsent-repro/results/predictions/main_pragmatic/vipragsent_full/20260520.jsonl",
      "status": "complete"
    },
    "hard_label_distillation": {
      "reason": "No teacher-logit or hard-label distillation training run is implemented in this protocol.",
      "status": "not_run"
    },
    "no_emotion_auxiliary": {
      "ece": 0.14246408445028735,
      "macro_pragmatic_f1": 74.8132,
      "ordinary_f1": null,
      "prediction_file": "/root/vipragsent-repro/results/predictions/main_pragmatic/vipragsent_no_emotion/20260520.jsonl",
      "status": "complete"
    },
    "no_explanation_cot_auxiliary": {
      "ece": 0.07841833389403831,
      "macro_pragmatic_f1": 73.6435,
      "ordinary_f1": null,
      "prediction_file": "/root/vipragsent-repro/results/predictions/main_pragmatic/vipragsent_no_rationale/20260520.jsonl",
      "status": "complete"
    },
    "no_multitask": {
      "ece": 0.08969743262926051,
      "macro_pragmatic_f1": 81.7177,
      "ordinary_f1": null,
      "prediction_file": "/root/vipragsent-repro/results/predictions/main_pragmatic/phobert_finetune/20260520.jsonl",
      "status": "complete"
    },
    "no_ordinary_sentiment_auxiliary": {
      "ece": 0.12214876163128928,
      "macro_pragmatic_f1": 73.358,
      "ordinary_f1": null,
      "prediction_file": "/root/vipragsent-repro/results/predictions/main_pragmatic/vipragsent_no_polarity/20260520.jsonl",
      "status": "complete"
    },
    "no_task_uncertainty_weighting": {
      "ece": 0.06504932543197298,
      "macro_pragmatic_f1": 73.6219,
      "ordinary_f1": null,
      "prediction_file": "/root/vipragsent-repro/results/predictions/main_pragmatic/vipragsent_no_uncertainty/20260520.jsonl",
      "status": "complete"
    }
  },
  "schema_version": "1.0",
  "status": "complete"
}
